{"game":{"races_count":0,"name":"155\u70ed\u8840\u4e09\u56fd","company":"UU\u6e38\u620f","average_rating":0.0,"areas_count":0,"servers":[{"name":"\u5173\u516c\u663e\u5723","created_at":"2010-04-28T11:53:11+08:00","updated_at":"2010-04-28T11:53:11+08:00","area_id":null,"id":10364,"ip":null,"game_id":488},{"name":"\u897f\u51c9\u9a6c\u8d85","created_at":"2010-04-28T11:53:11+08:00","updated_at":"2010-04-28T11:53:11+08:00","area_id":null,"id":10365,"ip":null,"game_id":488},{"name":"\u4e09\u987e\u8305\u5e90","created_at":"2010-04-28T11:53:11+08:00","updated_at":"2010-04-28T11:53:11+08:00","area_id":null,"id":10366,"ip":null,"game_id":488},{"name":"\u8d64\u58c1\u51dd\u4e91","created_at":"2010-04-28T11:53:11+08:00","updated_at":"2010-04-28T11:53:11+08:00","area_id":null,"id":10367,"ip":null,"game_id":488},{"name":"\u98ce\u4e91\u9645\u4f1a","created_at":"2010-04-28T11:53:11+08:00","updated_at":"2010-04-28T11:53:11+08:00","area_id":null,"id":10368,"ip":null,"game_id":488},{"name":"\u9b4f\u6b66\u98de\u97ad","created_at":"2010-04-28T11:53:11+08:00","updated_at":"2010-04-28T11:53:11+08:00","area_id":null,"id":10369,"ip":null,"game_id":488},{"name":"\u9f99\u98de\u51e4\u821e","created_at":"2010-04-28T11:53:11+08:00","updated_at":"2010-04-28T11:53:11+08:00","area_id":null,"id":10370,"ip":null,"game_id":488},{"name":"\u503e\u57ce\u4e00\u6218","created_at":"2010-04-28T11:53:11+08:00","updated_at":"2010-04-28T11:53:11+08:00","area_id":null,"id":10371,"ip":null,"game_id":488},{"name":"\u70fd\u706b\u4e4b\u6218","created_at":"2010-04-28T11:53:11+08:00","updated_at":"2010-04-28T11:53:11+08:00","area_id":null,"id":10372,"ip":null,"game_id":488}],"created_at":"2010-04-28T11:50:28+08:00","stop_running":false,"pinyin":"155rexuesanguo","official_web":"http://www.155game.com/rxsg/","updated_at":"2010-04-28T11:53:23+08:00","areas":[],"characters_count":0,"professions_count":0,"id":488,"professions":[],"last_week_characters_count":0,"attentions_count":0,"agent":"UU\u6e38\u620f","races":[],"sale_date":"2008-06-03","ratings_count":0,"description":"\u7b56\u7565\u8fd0\u8425\u7c7b\u7f51\u9875\u6e38\u620f","comments_count":0,"servers_count":9,"last_week_attentions_count":0}}